MANIFEST.in
README.rst
setup.py
aliyun_python_sdk_cloudwf.egg-info/PKG-INFO
aliyun_python_sdk_cloudwf.egg-info/SOURCES.txt
aliyun_python_sdk_cloudwf.egg-info/dependency_links.txt
aliyun_python_sdk_cloudwf.egg-info/requires.txt
aliyun_python_sdk_cloudwf.egg-info/top_level.txt
aliyunsdkcloudwf/__init__.py
aliyunsdkcloudwf/request/__init__.py
aliyunsdkcloudwf/request/v20170328/AddApgroupConfigRequest.py
aliyunsdkcloudwf/request/v20170328/AliyunRegisterApAssetRequest.py
aliyunsdkcloudwf/request/v20170328/ApgroupBatchAddApRequest.py
aliyunsdkcloudwf/request/v20170328/ApgroupBatchDeleteApRequest.py
aliyunsdkcloudwf/request/v20170328/AreaCreateRequest.py
aliyunsdkcloudwf/request/v20170328/AreaDeleteRequest.py
aliyunsdkcloudwf/request/v20170328/AreaInfoRequest.py
aliyunsdkcloudwf/request/v20170328/AreaShowListRequest.py
aliyunsdkcloudwf/request/v20170328/AreaUpdateRequest.py
aliyunsdkcloudwf/request/v20170328/BatchChangeGroupApNameRequest.py
aliyunsdkcloudwf/request/v20170328/BatchRegisterApAssetRequest.py
aliyunsdkcloudwf/request/v20170328/BatchSaveApPositionRequest.py
aliyunsdkcloudwf/request/v20170328/BusinessCreateRequest.py
aliyunsdkcloudwf/request/v20170328/BusinessInfoRequest.py
aliyunsdkcloudwf/request/v20170328/BusinessShowListRequest.py
aliyunsdkcloudwf/request/v20170328/BusinessUpdateRequest.py
aliyunsdkcloudwf/request/v20170328/CeaseInstanceRequest.py
aliyunsdkcloudwf/request/v20170328/CheckRootPermissionRequest.py
aliyunsdkcloudwf/request/v20170328/CheckUmengDataAnalysisPermissionRequest.py
aliyunsdkcloudwf/request/v20170328/ConfigAutoRenewRequest.py
aliyunsdkcloudwf/request/v20170328/CreateRenewOrderRequest.py
aliyunsdkcloudwf/request/v20170328/CreateSubAccountPermissionRequest.py
aliyunsdkcloudwf/request/v20170328/DelApPositionRequest.py
aliyunsdkcloudwf/request/v20170328/DelPageConfigTemplateRequest.py
aliyunsdkcloudwf/request/v20170328/DelPortalTempRequest.py
aliyunsdkcloudwf/request/v20170328/DelSubAccountPermissionRequest.py
aliyunsdkcloudwf/request/v20170328/DelUmengPagePermission4RootRequest.py
aliyunsdkcloudwf/request/v20170328/DeleteApRadioSsidConfigRequest.py
aliyunsdkcloudwf/request/v20170328/DeleteApgroupConfigRequest.py
